h5_models/__init__.py
midis/__init__.py
polymuse/__init__.py
polymuse/__main__.py
polymuse/builder.py
polymuse/constant.py
polymuse/data_generator.py
polymuse/dataset.py
polymuse/dataset2.py
polymuse/drawer.py
polymuse/dutils.py
polymuse/enc_deco.py
polymuse/evaluation.py
polymuse/generator.py
polymuse/generator_.py
polymuse/loader.py
polymuse/losses.py
polymuse/multi_track.py
polymuse/pattern.py
polymuse/player.py
polymuse/rnn.py
polymuse/rnn_gpu.py
polymuse/rnn_h.py
polymuse/rnn_player.py
polymuse/train.py
polymuse/transformer.py
polymuse_future-0.0.81.dist-info/LICENSE
polymuse_future-0.0.81.dist-info/METADATA
polymuse_future-0.0.81.dist-info/WHEEL
polymuse_future-0.0.81.dist-info/entry_points.txt
polymuse_future-0.0.81.dist-info/top_level.txt
polymuse_future-0.0.81.dist-info/RECORD
